synpro/__init__.py
synpro/base.py
synpro/data_sampler.py
synpro/data_transformer.py
synpro/errors.py
synpro/model.py
synpro-0.1.0.dist-info/LICENSE
synpro-0.1.0.dist-info/METADATA
synpro-0.1.0.dist-info/WHEEL
synpro-0.1.0.dist-info/top_level.txt
synpro-0.1.0.dist-info/RECORD
